{
  "__comment": "Designed by rndmaccess with BDcraft Cubik PRO 0.95 Beta - http://bdcraft.net", 
  "parent": "block/block",
  "textures":
  {
    "particle": "block/brown_wool",
    "brownWool": "block/brown_wool",
    "blackWool": "block/black_wool",
    "pinkWool": "block/pink_wool",
    "whiteWool": "block/white_wool",
    "whiteBrownWoolTop": "vanillaexpansions:block/white_brown_wool_top",
    "brownWhiteWoolSide": "vanillaexpansions:block/brown_white_wool"
  },
  "elements":
  [
    {
      "__comment": "Body", 
      "from": [ 5, 3, 5.5 ],
      "to": [ 11, 8, 13.5 ],
      "rotation": 
      {
        "origin": [ 5, 8, 5.5 ],
        "axis": "x",
        "angle": 22.5
      },
      "faces":
      {
        "down": { "uv": [ 5, 11.5, 11, 3.5 ], "texture": "#whiteBrownWoolTop" }, 
        "up": { "uv": [ 5, 3.586583, 11, 11.58658 ], "texture": "#whiteBrownWoolTop" }, 
        "north": { "uv": [ 5, 7.619398, 11, 12.6194 ], "texture": "#whiteWool" }, 
        "south": { "uv": [ 5, 7.619398, 11, 12.6194 ], "texture": "#brownWool" }, 
        "west": { "uv": [ 14.5, 4, 3.5, 11 ], "texture": "#brownWhiteWoolSide" }, 
        "east": { "uv": [ 3.5, 4, 14.5, 11 ], "texture": "#brownWhiteWoolSide" } 
      }
    },
    {
      "__comment": "Tail", 
      "from": [ 6.5, 2, 12 ],
      "to": [ 9.5, 4.5, 15 ],
      "rotation": 
      {
        "origin": [ 6.5, 4.5, 12 ],
        "axis": "x",
        "angle": 22.5
      },
      "faces":
      {
        "down": { "uv": [ 6.5, 1.956709, 9.5, 4.956709 ], "texture": "#brownWool" }, 
        "up": { "uv": [ 6.5, 11.04329, 9.5, 14.04329 ], "texture": "#brownWool" }, 
        "north": { "uv": [ 6.5, 11.3097, 9.5, 13.8097 ], "texture": "#brownWool" }, 
        "south": { "uv": [ 6.5, 11.3097, 9.5, 13.8097 ], "texture": "#brownWool" }, 
        "west": { "uv": [ 11.04329, 11.3097, 14.04329, 13.8097 ], "texture": "#brownWool" }, 
        "east": { "uv": [ 1.956709, 11.3097, 4.956709, 13.8097 ], "texture": "#brownWool" } 
      }
    },
    {
      "__comment": "RightHip", 
      "from": [ 3.5, 2.5, 6 ],
      "to": [ 5, 7, 12 ],
      "rotation": 
      {
        "origin": [ 3.5, 7, 6.5 ],
        "axis": "x",
        "angle": 22.5
      },
      "faces":
      {
        "down": { "uv": [ 3.5, 5.684015, 5, 11.68402 ], "texture": "#brownWool" }, 
        "up": { "uv": [ 3.5, 4.315985, 5, 10.31598 ], "texture": "#brownWool" }, 
        "north": { "uv": [ 11, 8.466116, 12.5, 12.96612 ], "texture": "#brownWool" }, 
        "south": { "uv": [ 3.5, 8.466116, 5, 12.96612 ], "texture": "#brownWool" }, 
        "west": { "uv": [ 4.315985, 8.466116, 10.31598, 12.96612 ], "texture": "#brownWool" }, 
        "east": { "uv": [ 5.684015, 8.466116, 11.68402, 12.96612 ], "texture": "#brownWool" } 
      }
    },
    {
      "__comment": "RightFoot", 
      "from": [ 3, 0, 5 ],
      "to": [ 5.5, 1.5, 10.5 ],
      "faces":
      {
        "down": { "uv": [ 3, 5.5, 5.5, 11 ], "texture": "#whiteWool" }, 
        "up": { "uv": [ 3, 5, 5.5, 10.5 ], "texture": "#whiteWool" }, 
        "north": { "uv": [ 10.5, 14.5, 13, 16 ], "texture": "#whiteWool" }, 
        "south": { "uv": [ 3, 14.5, 5.5, 16 ], "texture": "#whiteWool" }, 
        "west": { "uv": [ 5, 14.5, 10.5, 16 ], "texture": "#whiteWool" }, 
        "east": { "uv": [ 5.5, 14.5, 11, 16 ], "texture": "#whiteWool" } 
      }
    },
    {
      "__comment": "LeftHip", 
      "from": [ 11, 2.5, 6 ],
      "to": [ 12.5, 7, 12 ],
      "rotation": 
      {
        "origin": [ 11, 7, 6.5 ],
        "axis": "x",
        "angle": 22.5
      },
      "faces":
      {
        "down": { "uv": [ 11, 5.684015, 12.5, 11.68402 ], "texture": "#brownWool" }, 
        "up": { "uv": [ 11, 4.315985, 12.5, 10.31598 ], "texture": "#brownWool" }, 
        "north": { "uv": [ 3.5, 8.466116, 5, 12.96612 ], "texture": "#brownWool" }, 
        "south": { "uv": [ 11, 8.466116, 12.5, 12.96612 ], "texture": "#brownWool" }, 
        "west": { "uv": [ 4.315985, 8.466116, 10.31598, 12.96612 ], "texture": "#brownWool" }, 
        "east": { "uv": [ 5.684015, 8.466116, 11.68402, 12.96612 ], "texture": "#brownWool" } 
      }
    },
    {
      "__comment": "LeftFoot", 
      "from": [ 10.5, 0, 5 ],
      "to": [ 13, 1.5, 10.5 ],
      "faces":
      {
        "down": { "uv": [ 10.5, 5.5, 13, 11 ], "texture": "#whiteWool" }, 
        "up": { "uv": [ 10.5, 5, 13, 10.5 ], "texture": "#whiteWool" }, 
        "north": { "uv": [ 3, 14.5, 5.5, 16 ], "texture": "#whiteWool" }, 
        "south": { "uv": [ 10.5, 14.5, 13, 16 ], "texture": "#whiteWool" }, 
        "west": { "uv": [ 5, 14.5, 10.5, 16 ], "texture": "#whiteWool" }, 
        "east": { "uv": [ 5.5, 14.5, 11, 16 ], "texture": "#whiteWool" } 
      }
    },
    {
      "__comment": "LeftFrontLeg", 
      "from": [ 10.5, 0, 3.5 ],
      "to": [ 12, 6.5, 5 ],
      "faces":
      {
        "down": { "uv": [ 10.5, 11, 12, 12.5 ], "texture": "#brownWool" }, 
        "up": { "uv": [ 10.5, 3.5, 12, 5 ], "texture": "#brownWool" }, 
        "north": { "uv": [ 4, 9.5, 5.5, 16 ], "texture": "#brownWool" }, 
        "south": { "uv": [ 10.5, 9.5, 12, 16 ], "texture": "#brownWool" }, 
        "west": { "uv": [ 3.5, 9.5, 5, 16 ], "texture": "#brownWool" }, 
        "east": { "uv": [ 11, 9.5, 12.5, 16 ], "texture": "#brownWool" } 
      }
    },
    {
      "__comment": "RightFrontLeg", 
      "from": [ 4, 0, 3.5 ],
      "to": [ 5.5, 6.5, 5 ],
      "faces":
      {
        "down": { "uv": [ 4, 11, 5.5, 12.5 ], "texture": "#brownWool" }, 
        "up": { "uv": [ 4, 3.5, 5.5, 5 ], "texture": "#brownWool" }, 
        "north": { "uv": [ 10.5, 9.5, 12, 16 ], "texture": "#brownWool" }, 
        "south": { "uv": [ 4, 9.5, 5.5, 16 ], "texture": "#brownWool" }, 
        "west": { "uv": [ 3.5, 9.5, 5, 16 ], "texture": "#brownWool" }, 
        "east": { "uv": [ 11, 9.5, 12.5, 16 ], "texture": "#brownWool" } 
      }
    },
    {
      "__comment": "Head", 
      "from": [ 5.5, 6.5, 1.5 ],
      "to": [ 10.5, 10.5, 6 ],
      "faces":
      {
        "down": { "uv": [ 5.5, 10, 10.5, 14.5 ], "texture": "#brownWool" }, 
        "up": { "uv": [ 5.5, 1.5, 10.5, 6 ], "texture": "#brownWool" }, 
        "north": { "uv": [ 5.5, 5.5, 10.5, 9.5 ], "texture": "#brownWool" }, 
        "south": { "uv": [ 5.5, 5.5, 10.5, 9.5 ], "texture": "#brownWool" }, 
        "west": { "uv": [ 1.5, 5.5, 6, 9.5 ], "texture": "#brownWool" }, 
        "east": { "uv": [ 10, 5.5, 14.5, 9.5 ], "texture": "#brownWool" } 
      }
    },
    {
      "__comment": "Nose", 
      "from": [ 7.5, 7.5, 1 ],
      "to": [ 8.5, 8.5, 1.5 ],
      "faces":
      {
        "down": { "uv": [ 7.5, 14.5, 8.5, 15 ], "texture": "#pinkWool" }, 
        "up": { "uv": [ 7.5, 1, 8.5, 1.5 ], "texture": "#pinkWool" }, 
        "north": { "uv": [ 7.5, 7.5, 8.5, 8.5 ], "texture": "#pinkWool" }, 
        "west": { "uv": [ 1, 7.5, 1.5, 8.5 ], "texture": "#pinkWool" }, 
        "east": { "uv": [ 14.5, 7.5, 15, 8.5 ], "texture": "#pinkWool" } 
      }
    },
    {
      "__comment": "LeftEye", 
      "from": [ 8.5, 8.5, 1 ],
      "to": [ 9.5, 10, 1.5 ],
      "faces":
      {
        "down": { "uv": [ 8.5, 14.5, 9.5, 15 ], "texture": "#blackWool" }, 
        "up": { "uv": [ 8.5, 1, 9.5, 1.5 ], "texture": "#blackWool" }, 
        "north": { "uv": [ 6.5, 6, 7.5, 7.5 ], "texture": "#blackWool" }, 
        "west": { "uv": [ 1, 6, 1.5, 7.5 ], "texture": "#blackWool" }, 
        "east": { "uv": [ 14.5, 6, 15, 7.5 ], "texture": "#blackWool" } 
      }
    },
    {
      "__comment": "RightEye", 
      "from": [ 6.5, 8.5, 1 ],
      "to": [ 7.5, 10, 1.5 ],
      "faces":
      {
        "down": { "uv": [ 6.5, 14.5, 7.5, 15 ], "texture": "#blackWool" }, 
        "up": { "uv": [ 6.5, 1, 7.5, 1.5 ], "texture": "#blackWool" }, 
        "north": { "uv": [ 8.5, 6, 9.5, 7.5 ], "texture": "#blackWool" }, 
        "west": { "uv": [ 1, 6, 1.5, 7.5 ], "texture": "#blackWool" }, 
        "east": { "uv": [ 14.5, 6, 15, 7.5 ], "texture": "#blackWool" } 
      }
    },
    {
      "__comment": "LeftEar", 
      "from": [ 8.5, 10.5, 4 ],
      "to": [ 9.5, 13.5, 4.5 ],
      "rotation": 
      {
        "origin": [ 8.5, 10.5, 4 ],
        "axis": "y",
        "angle": 45
      },
      "faces":
      {
        "up": { "uv": [ 8.5, 4, 9.5, 4.5 ], "texture": "#brownWool" }, 
        "north": { "uv": [ 6.5, 2.5, 7.5, 5.5 ], "texture": "#pinkWool" }, 
        "south": { "uv": [ 8.5, 2.5, 9.5, 5.5 ], "texture": "#brownWool" }, 
        "west": { "uv": [ 4, 2.5, 4.5, 5.5 ], "texture": "#brownWool" }, 
        "east": { "uv": [ 11.5, 2.5, 12, 5.5 ], "texture": "#brownWool" } 
      }
    },
    {
      "__comment": "RightEar", 
      "from": [ 6.5, 10.5, 3 ],
      "to": [ 7.5, 13.5, 3.5 ],
      "rotation": 
      {
        "origin": [ 6.5, 10.5, 3 ],
        "axis": "y",
        "angle": -45
      },
      "faces":
      {
        "up": { "uv": [ 6.5, 3, 7.5, 3.5 ], "texture": "#brownWool" }, 
        "north": { "uv": [ 8.5, 2.5, 9.5, 5.5 ], "texture": "#pinkWool" }, 
        "south": { "uv": [ 6.5, 2.5, 7.5, 5.5 ], "texture": "#brownWool" }, 
        "west": { "uv": [ 3, 2.5, 3.5, 5.5 ], "texture": "#brownWool" }, 
        "east": { "uv": [ 12.5, 2.5, 13, 5.5 ], "texture": "#brownWool" } 
      }
    },
    {
      "__comment": "RightEarTuff", 
      "from": [ 6.5, 13.5, 3 ],
      "to": [ 7.5, 14, 3.5 ],
      "rotation": 
      {
        "origin": [ 6.5, 13.5, 3 ],
        "axis": "y",
        "angle": -45
      },
      "faces":
      {
        "up": { "uv": [ 6.5, 3, 7.5, 3.5 ], "texture": "#brownWool" }, 
        "north": { "uv": [ 8.5, 2, 9.5, 2.5 ], "texture": "#brownWool" }, 
        "south": { "uv": [ 6.5, 2, 7.5, 2.5 ], "texture": "#brownWool" }, 
        "west": { "uv": [ 3, 2, 3.5, 2.5 ], "texture": "#brownWool" }, 
        "east": { "uv": [ 12.5, 2, 13, 2.5 ], "texture": "#brownWool" } 
      }
    },
    {
      "__comment": "LeftEarTuff", 
      "from": [ 8.5, 13.5, 4 ],
      "to": [ 9.5, 14, 4.5 ],
      "rotation": 
      {
        "origin": [ 8.5, 13.5, 4 ],
        "axis": "y",
        "angle": 45
      },
      "faces":
      {
        "up": { "uv": [ 8.5, 4, 9.5, 4.5 ], "texture": "#brownWool" }, 
        "north": { "uv": [ 6.5, 2, 7.5, 2.5 ], "texture": "#brownWool" }, 
        "south": { "uv": [ 8.5, 2, 9.5, 2.5 ], "texture": "#brownWool" }, 
        "west": { "uv": [ 4, 2, 4.5, 2.5 ], "texture": "#brownWool" }, 
        "east": { "uv": [ 11.5, 2, 12, 2.5 ], "texture": "#brownWool" } 
      }
    }
  ]
}
